{
  "demoFile": "2026-06-12__0305__1__27180486__de_dust2__team-canalha__vs__team-kingc-j.dem",
  "map": "de_dust2",
  "server": "Registre-se e jogue @ gamersclub.com.br",
  "officialStartTick": 11459,
  "officialEndTick": 163483,
  "rounds": 22,
  "winnerTeam": 3,
  "teamSummary": [
    {
      "team": 3,
      "kills": 77,
      "deaths": 65,
      "diff": 12
    },
    {
      "team": 2,
      "kills": 65,
      "deaths": 77,
      "diff": -12
    }
  ],
  "mvp": {
    "name": "⑬ ☆ T0M[1]...:P",
    "steamid": "76561198827102122",
    "mvpScore": 63.85
  },
  "players": [
    {
      "name": "⑬ ☆ T0M[1]...:P",
      "steamid": "76561198827102122",
      "team": 3,
      "kills": 28,
      "assists": 7,
      "deaths": 11,
      "headshots": 8,
      "damage": 2778,
      "entryKills": 8,
      "entryDeaths": 1,
      "openingKills": 8,
      "openingDeaths": 1,
      "openingDuels": 9,
      "tradeKills": 5,
      "tradeOpportunities": 0,
      "awpKills": 8,
      "twoKs": 6,
      "threeKs": 1,
      "fourKs": 1,
      "aces": 0,
      "clutch1v1": 0,
      "clutch1v2": 0,
      "clutch1v3": 1,
      "clutch1v4": 0,
      "clutch1v5": 0,
      "baitRounds": 4,
      "kastRounds": 19,
      "heDamage": 70,
      "flashAssists": 0,
      "molotovDamage": 32,
      "ctKills": 10,
      "ctDeaths": 7,
      "tKills": 18,
      "tDeaths": 4,
      "weapons": {
        "glock": 1,
        "ssg08": 4,
        "awp": 8,
        "ak47": 4,
        "hegrenade": 1,
        "p250": 1,
        "m4a1_silencer": 8,
        "mp9": 1
      },
      "diff": 17,
      "kd": 2.55,
      "hsPercent": 28.57,
      "adr": 126.27,
      "entryRatio": 8,
      "totalClutches": 1,
      "kastPercent": 86.36,
      "impactRating": 1.59,
      "openingDuelWinPercent": 88.89,
      "firstKillPercent": 36.36,
      "tradeKillPercent": 17.86,
      "ctKd": 1.43,
      "tKd": 4.5,
      "favoriteWeapon": {
        "weapon": "awp",
        "kills": 8
      },
      "ratingS4N": 2.32,
      "mvpScore": 63.85
    },
    {
      "name": "⑧ ☆ kingC.- J",
      "steamid": "76561198810129628",
      "team": 3,
      "kills": 18,
      "assists": 4,
      "deaths": 13,
      "headshots": 5,
      "damage": 1841,
      "entryKills": 1,
      "entryDeaths": 4,
      "openingKills": 1,
      "openingDeaths": 4,
      "openingDuels": 5,
      "tradeKills": 3,
      "tradeOpportunities": 0,
      "awpKills": 2,
      "twoKs": 2,
      "threeKs": 0,
      "fourKs": 2,
      "aces": 0,
      "clutch1v1": 0,
      "clutch1v2": 0,
      "clutch1v3": 1,
      "clutch1v4": 0,
      "clutch1v5": 0,
      "baitRounds": 3,
      "kastRounds": 17,
      "heDamage": 6,
      "flashAssists": 1,
      "molotovDamage": 95,
      "ctKills": 11,
      "ctDeaths": 7,
      "tKills": 7,
      "tDeaths": 6,
      "weapons": {
        "glock": 1,
        "mac10": 4,
        "m4a1_silencer": 3,
        "m4a1": 1,
        "deagle": 2,
        "usp_silencer": 2,
        "mp9": 1,
        "awp": 2,
        "fiveseven": 1,
        "ak47": 1
      },
      "diff": 5,
      "kd": 1.38,
      "hsPercent": 27.78,
      "adr": 83.68,
      "entryRatio": 0.25,
      "totalClutches": 1,
      "kastPercent": 77.27,
      "impactRating": 1,
      "openingDuelWinPercent": 20,
      "firstKillPercent": 4.55,
      "tradeKillPercent": 16.67,
      "ctKd": 1.57,
      "tKd": 1.17,
      "favoriteWeapon": {
        "weapon": "mac10",
        "kills": 4
      },
      "ratingS4N": 1.07,
      "mvpScore": 34.53
    },
    {
      "name": "⑫ ✓ xshaaanzy",
      "steamid": "76561199759664002",
      "team": 2,
      "kills": 17,
      "assists": 3,
      "deaths": 15,
      "headshots": 8,
      "damage": 1852,
      "entryKills": 5,
      "entryDeaths": 3,
      "openingKills": 5,
      "openingDeaths": 3,
      "openingDuels": 8,
      "tradeKills": 1,
      "tradeOpportunities": 0,
      "awpKills": 0,
      "twoKs": 2,
      "threeKs": 0,
      "fourKs": 1,
      "aces": 0,
      "clutch1v1": 0,
      "clutch1v2": 0,
      "clutch1v3": 1,
      "clutch1v4": 0,
      "clutch1v5": 0,
      "baitRounds": 4,
      "kastRounds": 14,
      "heDamage": 41,
      "flashAssists": 1,
      "molotovDamage": 0,
      "ctKills": 9,
      "ctDeaths": 7,
      "tKills": 8,
      "tDeaths": 8,
      "weapons": {
        "usp_silencer": 1,
        "m4a1_silencer": 5,
        "mp9": 1,
        "m4a1": 1,
        "glock": 1,
        "ak47": 7,
        "hegrenade": 1
      },
      "diff": 2,
      "kd": 1.13,
      "hsPercent": 47.06,
      "adr": 84.18,
      "entryRatio": 1.67,
      "totalClutches": 1,
      "kastPercent": 63.64,
      "impactRating": 0.91,
      "openingDuelWinPercent": 62.5,
      "firstKillPercent": 22.73,
      "tradeKillPercent": 5.88,
      "ctKd": 1.29,
      "tKd": 1,
      "favoriteWeapon": {
        "weapon": "ak47",
        "kills": 7
      },
      "ratingS4N": 1.07,
      "mvpScore": 32.76
    },
    {
      "name": "⑬ ILUMIN4RI",
      "steamid": "76561199037068708",
      "team": 3,
      "kills": 16,
      "assists": 7,
      "deaths": 12,
      "headshots": 7,
      "damage": 1691,
      "entryKills": 0,
      "entryDeaths": 5,
      "openingKills": 0,
      "openingDeaths": 5,
      "openingDuels": 5,
      "tradeKills": 4,
      "tradeOpportunities": 0,
      "awpKills": 0,
      "twoKs": 4,
      "threeKs": 0,
      "fourKs": 0,
      "aces": 0,
      "clutch1v1": 0,
      "clutch1v2": 0,
      "clutch1v3": 0,
      "clutch1v4": 0,
      "clutch1v5": 0,
      "baitRounds": 3,
      "kastRounds": 18,
      "heDamage": 130,
      "flashAssists": 0,
      "molotovDamage": 0,
      "ctKills": 6,
      "ctDeaths": 6,
      "tKills": 10,
      "tDeaths": 6,
      "weapons": {
        "glock": 3,
        "galilar": 1,
        "ak47": 6,
        "elite": 1,
        "m4a1_silencer": 1,
        "m4a1": 2,
        "fiveseven": 1,
        "mp9": 1
      },
      "diff": 4,
      "kd": 1.33,
      "hsPercent": 43.75,
      "adr": 76.86,
      "entryRatio": 0,
      "totalClutches": 0,
      "kastPercent": 81.82,
      "impactRating": 1.05,
      "openingDuelWinPercent": 0,
      "firstKillPercent": 0,
      "tradeKillPercent": 25,
      "ctKd": 1,
      "tKd": 1.67,
      "favoriteWeapon": {
        "weapon": "ak47",
        "kills": 6
      },
      "ratingS4N": 1.03,
      "mvpScore": 30.6
    },
    {
      "name": "⑭ ☆ Canalha",
      "steamid": "76561199443753255",
      "team": 2,
      "kills": 13,
      "assists": 5,
      "deaths": 16,
      "headshots": 8,
      "damage": 1633,
      "entryKills": 3,
      "entryDeaths": 1,
      "openingKills": 3,
      "openingDeaths": 1,
      "openingDuels": 4,
      "tradeKills": 2,
      "tradeOpportunities": 0,
      "awpKills": 2,
      "twoKs": 4,
      "threeKs": 0,
      "fourKs": 0,
      "aces": 0,
      "clutch1v1": 0,
      "clutch1v2": 0,
      "clutch1v3": 0,
      "clutch1v4": 0,
      "clutch1v5": 0,
      "baitRounds": 2,
      "kastRounds": 13,
      "heDamage": 44,
      "flashAssists": 2,
      "molotovDamage": 12,
      "ctKills": 4,
      "ctDeaths": 10,
      "tKills": 9,
      "tDeaths": 6,
      "weapons": {
        "usp_silencer": 2,
        "m4a1_silencer": 3,
        "ak47": 6,
        "awp": 2
      },
      "diff": -3,
      "kd": 0.81,
      "hsPercent": 61.54,
      "adr": 74.23,
      "entryRatio": 3,
      "totalClutches": 0,
      "kastPercent": 59.09,
      "impactRating": 0.82,
      "openingDuelWinPercent": 75,
      "firstKillPercent": 13.64,
      "tradeKillPercent": 15.38,
      "ctKd": 0.4,
      "tKd": 1.5,
      "favoriteWeapon": {
        "weapon": "ak47",
        "kills": 6
      },
      "ratingS4N": 0.98,
      "mvpScore": 21.65
    },
    {
      "name": "⑨ ✓ ☆ qony",
      "steamid": "76561199392187332",
      "team": 2,
      "kills": 17,
      "assists": 3,
      "deaths": 16,
      "headshots": 8,
      "damage": 1673,
      "entryKills": 1,
      "entryDeaths": 0,
      "openingKills": 1,
      "openingDeaths": 0,
      "openingDuels": 1,
      "tradeKills": 2,
      "tradeOpportunities": 0,
      "awpKills": 3,
      "twoKs": 3,
      "threeKs": 1,
      "fourKs": 0,
      "aces": 0,
      "clutch1v1": 0,
      "clutch1v2": 0,
      "clutch1v3": 0,
      "clutch1v4": 0,
      "clutch1v5": 0,
      "baitRounds": 9,
      "kastRounds": 16,
      "heDamage": 44,
      "flashAssists": 0,
      "molotovDamage": 0,
      "ctKills": 10,
      "ctDeaths": 9,
      "tKills": 7,
      "tDeaths": 7,
      "weapons": {
        "m4a1_silencer": 1,
        "m4a1": 3,
        "awp": 3,
        "glock": 2,
        "ak47": 8
      },
      "diff": 1,
      "kd": 1.06,
      "hsPercent": 47.06,
      "adr": 76.05,
      "entryRatio": 1,
      "totalClutches": 0,
      "kastPercent": 72.73,
      "impactRating": 0.91,
      "openingDuelWinPercent": 100,
      "firstKillPercent": 4.55,
      "tradeKillPercent": 11.76,
      "ctKd": 1.11,
      "tKd": 1,
      "favoriteWeapon": {
        "weapon": "ak47",
        "kills": 8
      },
      "ratingS4N": 0.96,
      "mvpScore": 27.19
    },
    {
      "name": "⑧ ☆ Ludo",
      "steamid": "76561198072925518",
      "team": 3,
      "kills": 10,
      "assists": 4,
      "deaths": 15,
      "headshots": 4,
      "damage": 1289,
      "entryKills": 1,
      "entryDeaths": 1,
      "openingKills": 1,
      "openingDeaths": 1,
      "openingDuels": 2,
      "tradeKills": 1,
      "tradeOpportunities": 0,
      "awpKills": 2,
      "twoKs": 3,
      "threeKs": 0,
      "fourKs": 0,
      "aces": 0,
      "clutch1v1": 0,
      "clutch1v2": 0,
      "clutch1v3": 0,
      "clutch1v4": 0,
      "clutch1v5": 0,
      "baitRounds": 6,
      "kastRounds": 17,
      "heDamage": 38,
      "flashAssists": 0,
      "molotovDamage": 21,
      "ctKills": 6,
      "ctDeaths": 9,
      "tKills": 4,
      "tDeaths": 6,
      "weapons": {
        "ak47": 6,
        "awp": 2,
        "mp9": 1,
        "m4a1_silencer": 1
      },
      "diff": -5,
      "kd": 0.67,
      "hsPercent": 40,
      "adr": 58.59,
      "entryRatio": 1,
      "totalClutches": 0,
      "kastPercent": 77.27,
      "impactRating": 0.64,
      "openingDuelWinPercent": 50,
      "firstKillPercent": 4.55,
      "tradeKillPercent": 10,
      "ctKd": 0.67,
      "tKd": 0.67,
      "favoriteWeapon": {
        "weapon": "ak47",
        "kills": 6
      },
      "ratingS4N": 0.68,
      "mvpScore": 14.69
    },
    {
      "name": "⑧ Comedor de xana",
      "steamid": "76561198289253809",
      "team": 2,
      "kills": 10,
      "assists": 4,
      "deaths": 18,
      "headshots": 3,
      "damage": 1257,
      "entryKills": 2,
      "entryDeaths": 3,
      "openingKills": 2,
      "openingDeaths": 3,
      "openingDuels": 5,
      "tradeKills": 0,
      "tradeOpportunities": 0,
      "awpKills": 0,
      "twoKs": 1,
      "threeKs": 0,
      "fourKs": 0,
      "aces": 0,
      "clutch1v1": 0,
      "clutch1v2": 0,
      "clutch1v3": 0,
      "clutch1v4": 0,
      "clutch1v5": 0,
      "baitRounds": 4,
      "kastRounds": 13,
      "heDamage": 39,
      "flashAssists": 0,
      "molotovDamage": 0,
      "ctKills": 2,
      "ctDeaths": 8,
      "tKills": 8,
      "tDeaths": 10,
      "weapons": {
        "m4a1": 3,
        "mp9": 1,
        "m4a1_silencer": 1,
        "ak47": 4,
        "mac10": 1
      },
      "diff": -8,
      "kd": 0.56,
      "hsPercent": 30,
      "adr": 57.14,
      "entryRatio": 0.67,
      "totalClutches": 0,
      "kastPercent": 59.09,
      "impactRating": 0.64,
      "openingDuelWinPercent": 40,
      "firstKillPercent": 9.09,
      "tradeKillPercent": 0,
      "ctKd": 0.25,
      "tKd": 0.8,
      "favoriteWeapon": {
        "weapon": "ak47",
        "kills": 4
      },
      "ratingS4N": 0.58,
      "mvpScore": 12.4
    },
    {
      "name": "⑩ ✓ ☆ SOLITARY",
      "steamid": "76561198880810687",
      "team": 2,
      "kills": 8,
      "assists": 4,
      "deaths": 12,
      "headshots": 0,
      "damage": 1138,
      "entryKills": 1,
      "entryDeaths": 3,
      "openingKills": 1,
      "openingDeaths": 3,
      "openingDuels": 4,
      "tradeKills": 2,
      "tradeOpportunities": 0,
      "awpKills": 1,
      "twoKs": 1,
      "threeKs": 0,
      "fourKs": 0,
      "aces": 0,
      "clutch1v1": 0,
      "clutch1v2": 0,
      "clutch1v3": 0,
      "clutch1v4": 0,
      "clutch1v5": 0,
      "baitRounds": 2,
      "kastRounds": 14,
      "heDamage": 99,
      "flashAssists": 0,
      "molotovDamage": 6,
      "ctKills": 4,
      "ctDeaths": 7,
      "tKills": 4,
      "tDeaths": 5,
      "weapons": {
        "taser": 1,
        "m4a1_silencer": 1,
        "ak47": 5,
        "awp": 1
      },
      "diff": -4,
      "kd": 0.67,
      "hsPercent": 0,
      "adr": 51.73,
      "entryRatio": 0.33,
      "totalClutches": 0,
      "kastPercent": 63.64,
      "impactRating": 0.55,
      "openingDuelWinPercent": 25,
      "firstKillPercent": 4.55,
      "tradeKillPercent": 25,
      "ctKd": 0.57,
      "tKd": 0.8,
      "favoriteWeapon": {
        "weapon": "ak47",
        "kills": 5
      },
      "ratingS4N": 0.54,
      "mvpScore": 12.6
    },
    {
      "name": "⑧ Nicolas",
      "steamid": "76561199082720391",
      "team": 3,
      "kills": 5,
      "assists": 6,
      "deaths": 14,
      "headshots": 2,
      "damage": 821,
      "entryKills": 0,
      "entryDeaths": 1,
      "openingKills": 0,
      "openingDeaths": 1,
      "openingDuels": 1,
      "tradeKills": 0,
      "tradeOpportunities": 0,
      "awpKills": 0,
      "twoKs": 0,
      "threeKs": 0,
      "fourKs": 0,
      "aces": 0,
      "clutch1v1": 0,
      "clutch1v2": 0,
      "clutch1v3": 0,
      "clutch1v4": 0,
      "clutch1v5": 0,
      "baitRounds": 4,
      "kastRounds": 16,
      "heDamage": 80,
      "flashAssists": 0,
      "molotovDamage": 4,
      "ctKills": 3,
      "ctDeaths": 7,
      "tKills": 2,
      "tDeaths": 7,
      "weapons": {
        "glock": 1,
        "ak47": 1,
        "mac10": 1,
        "mp9": 1,
        "m4a1": 1
      },
      "diff": -9,
      "kd": 0.36,
      "hsPercent": 40,
      "adr": 37.32,
      "entryRatio": 0,
      "totalClutches": 0,
      "kastPercent": 72.73,
      "impactRating": 0.5,
      "openingDuelWinPercent": 0,
      "firstKillPercent": 0,
      "tradeKillPercent": 0,
      "ctKd": 0.43,
      "tKd": 0.29,
      "favoriteWeapon": {
        "weapon": "glock",
        "kills": 1
      },
      "ratingS4N": 0.38,
      "mvpScore": 5.6
    }
  ],
  "createdAt": "2026-06-14T04:41:24.419Z"
}