{
  "demoFile": "2026-06-10__0220__1__27164541__de_dust2__team-cyclops-csro-__vs__team-kingc-j.dem",
  "map": "de_dust2",
  "server": "Registre-se e jogue @ gamersclub.com.br",
  "officialStartTick": 11695,
  "officialEndTick": 130098,
  "rounds": 18,
  "winnerTeam": 3,
  "teamSummary": [
    {
      "team": 3,
      "kills": 76,
      "deaths": 52,
      "diff": 24
    },
    {
      "team": 2,
      "kills": 52,
      "deaths": 76,
      "diff": -24
    }
  ],
  "mvp": {
    "name": "⑭ ✓ P3ter the Turtle",
    "steamid": "76561198369915204",
    "mvpScore": 44.78
  },
  "players": [
    {
      "name": "⑭ ✓ P3ter the Turtle",
      "steamid": "76561198369915204",
      "team": 3,
      "kills": 21,
      "assists": 4,
      "deaths": 9,
      "headshots": 9,
      "damage": 1946,
      "entryKills": 3,
      "entryDeaths": 1,
      "openingKills": 3,
      "openingDeaths": 1,
      "openingDuels": 4,
      "tradeKills": 3,
      "tradeOpportunities": 0,
      "awpKills": 7,
      "twoKs": 5,
      "threeKs": 1,
      "fourKs": 0,
      "aces": 0,
      "clutch1v1": 0,
      "clutch1v2": 0,
      "clutch1v3": 0,
      "clutch1v4": 0,
      "clutch1v5": 0,
      "baitRounds": 5,
      "kastRounds": 16,
      "heDamage": 42,
      "flashAssists": 0,
      "molotovDamage": 93,
      "ctKills": 14,
      "ctDeaths": 7,
      "tKills": 7,
      "tDeaths": 2,
      "weapons": {
        "galilar": 1,
        "ak47": 5,
        "m4a1_silencer": 6,
        "awp": 7,
        "usp_silencer": 2
      },
      "diff": 12,
      "kd": 2.33,
      "hsPercent": 42.86,
      "adr": 108.11,
      "entryRatio": 3,
      "totalClutches": 0,
      "kastPercent": 88.89,
      "impactRating": 1.39,
      "openingDuelWinPercent": 75,
      "firstKillPercent": 16.67,
      "tradeKillPercent": 14.29,
      "ctKd": 2,
      "tKd": 3.5,
      "favoriteWeapon": {
        "weapon": "awp",
        "kills": 7
      },
      "ratingS4N": 1.84,
      "mvpScore": 44.78
    },
    {
      "name": "⑬ ✓ VINICETINHA",
      "steamid": "76561197985216441",
      "team": 3,
      "kills": 18,
      "assists": 6,
      "deaths": 8,
      "headshots": 8,
      "damage": 1805,
      "entryKills": 3,
      "entryDeaths": 0,
      "openingKills": 3,
      "openingDeaths": 0,
      "openingDuels": 3,
      "tradeKills": 1,
      "tradeOpportunities": 0,
      "awpKills": 0,
      "twoKs": 2,
      "threeKs": 2,
      "fourKs": 0,
      "aces": 0,
      "clutch1v1": 0,
      "clutch1v2": 0,
      "clutch1v3": 0,
      "clutch1v4": 0,
      "clutch1v5": 0,
      "baitRounds": 1,
      "kastRounds": 16,
      "heDamage": 84,
      "flashAssists": 0,
      "molotovDamage": 0,
      "ctKills": 8,
      "ctDeaths": 7,
      "tKills": 10,
      "tDeaths": 1,
      "weapons": {
        "glock": 1,
        "ak47": 7,
        "usp_silencer": 2,
        "m4a1": 8
      },
      "diff": 10,
      "kd": 2.25,
      "hsPercent": 44.44,
      "adr": 100.28,
      "entryRatio": 3,
      "totalClutches": 0,
      "kastPercent": 88.89,
      "impactRating": 1.33,
      "openingDuelWinPercent": 100,
      "firstKillPercent": 16.67,
      "tradeKillPercent": 5.56,
      "ctKd": 1.14,
      "tKd": 10,
      "favoriteWeapon": {
        "weapon": "m4a1",
        "kills": 8
      },
      "ratingS4N": 1.78,
      "mvpScore": 40.77
    },
    {
      "name": "⑦ ☆ SonaCetinha",
      "steamid": "76561198150812214",
      "team": 3,
      "kills": 17,
      "assists": 7,
      "deaths": 14,
      "headshots": 9,
      "damage": 1931,
      "entryKills": 4,
      "entryDeaths": 2,
      "openingKills": 4,
      "openingDeaths": 2,
      "openingDuels": 6,
      "tradeKills": 5,
      "tradeOpportunities": 0,
      "awpKills": 0,
      "twoKs": 4,
      "threeKs": 1,
      "fourKs": 0,
      "aces": 0,
      "clutch1v1": 0,
      "clutch1v2": 0,
      "clutch1v3": 0,
      "clutch1v4": 0,
      "clutch1v5": 0,
      "baitRounds": 7,
      "kastRounds": 14,
      "heDamage": 121,
      "flashAssists": 0,
      "molotovDamage": 36,
      "ctKills": 12,
      "ctDeaths": 10,
      "tKills": 5,
      "tDeaths": 4,
      "weapons": {
        "glock": 3,
        "ak47": 7,
        "ssg08": 3,
        "usp_silencer": 1,
        "mp7": 1,
        "m4a1_silencer": 2
      },
      "diff": 3,
      "kd": 1.21,
      "hsPercent": 52.94,
      "adr": 107.28,
      "entryRatio": 2,
      "totalClutches": 0,
      "kastPercent": 77.78,
      "impactRating": 1.33,
      "openingDuelWinPercent": 66.67,
      "firstKillPercent": 22.22,
      "tradeKillPercent": 29.41,
      "ctKd": 1.2,
      "tKd": 1.25,
      "favoriteWeapon": {
        "weapon": "ak47",
        "kills": 7
      },
      "ratingS4N": 1.21,
      "mvpScore": 35.25
    },
    {
      "name": "⑬ ILUMIN4RI",
      "steamid": "76561199037068708",
      "team": 2,
      "kills": 13,
      "assists": 5,
      "deaths": 12,
      "headshots": 10,
      "damage": 1538,
      "entryKills": 1,
      "entryDeaths": 0,
      "openingKills": 1,
      "openingDeaths": 0,
      "openingDuels": 1,
      "tradeKills": 0,
      "tradeOpportunities": 0,
      "awpKills": 0,
      "twoKs": 2,
      "threeKs": 1,
      "fourKs": 0,
      "aces": 0,
      "clutch1v1": 0,
      "clutch1v2": 0,
      "clutch1v3": 0,
      "clutch1v4": 0,
      "clutch1v5": 0,
      "baitRounds": 3,
      "kastRounds": 15,
      "heDamage": 71,
      "flashAssists": 0,
      "molotovDamage": 17,
      "ctKills": 6,
      "ctDeaths": 5,
      "tKills": 7,
      "tDeaths": 7,
      "weapons": {
        "usp_silencer": 1,
        "ak47": 5,
        "m4a1": 1,
        "glock": 1,
        "mac10": 1,
        "galilar": 4
      },
      "diff": 1,
      "kd": 1.08,
      "hsPercent": 76.92,
      "adr": 85.44,
      "entryRatio": 1,
      "totalClutches": 0,
      "kastPercent": 83.33,
      "impactRating": 1,
      "openingDuelWinPercent": 100,
      "firstKillPercent": 5.56,
      "tradeKillPercent": 0,
      "ctKd": 1.2,
      "tKd": 1,
      "favoriteWeapon": {
        "weapon": "ak47",
        "kills": 5
      },
      "ratingS4N": 1.06,
      "mvpScore": 25.06
    },
    {
      "name": "⑪ ✓ ☆ Cyclops* -csro-",
      "steamid": "76561198216023735",
      "team": 3,
      "kills": 11,
      "assists": 4,
      "deaths": 10,
      "headshots": 7,
      "damage": 1230,
      "entryKills": 1,
      "entryDeaths": 2,
      "openingKills": 1,
      "openingDeaths": 2,
      "openingDuels": 3,
      "tradeKills": 1,
      "tradeOpportunities": 0,
      "awpKills": 0,
      "twoKs": 2,
      "threeKs": 1,
      "fourKs": 0,
      "aces": 0,
      "clutch1v1": 0,
      "clutch1v2": 0,
      "clutch1v3": 0,
      "clutch1v4": 0,
      "clutch1v5": 0,
      "baitRounds": 1,
      "kastRounds": 14,
      "heDamage": 0,
      "flashAssists": 0,
      "molotovDamage": 0,
      "ctKills": 10,
      "ctDeaths": 7,
      "tKills": 1,
      "tDeaths": 3,
      "weapons": {
        "p250": 2,
        "nova": 3,
        "deagle": 2,
        "ak47": 2,
        "m4a1_silencer": 1,
        "mp9": 1
      },
      "diff": 1,
      "kd": 1.1,
      "hsPercent": 63.64,
      "adr": 68.33,
      "entryRatio": 0.5,
      "totalClutches": 0,
      "kastPercent": 77.78,
      "impactRating": 0.83,
      "openingDuelWinPercent": 33.33,
      "firstKillPercent": 5.56,
      "tradeKillPercent": 9.09,
      "ctKd": 1.43,
      "tKd": 0.33,
      "favoriteWeapon": {
        "weapon": "nova",
        "kills": 3
      },
      "ratingS4N": 0.95,
      "mvpScore": 21.38
    },
    {
      "name": "⑩ ✓ ★ LuscaFusca",
      "steamid": "76561198189616162",
      "team": 3,
      "kills": 9,
      "assists": 4,
      "deaths": 11,
      "headshots": 3,
      "damage": 1274,
      "entryKills": 1,
      "entryDeaths": 1,
      "openingKills": 1,
      "openingDeaths": 1,
      "openingDuels": 2,
      "tradeKills": 1,
      "tradeOpportunities": 0,
      "awpKills": 0,
      "twoKs": 2,
      "threeKs": 0,
      "fourKs": 0,
      "aces": 0,
      "clutch1v1": 0,
      "clutch1v2": 0,
      "clutch1v3": 0,
      "clutch1v4": 0,
      "clutch1v5": 0,
      "baitRounds": 3,
      "kastRounds": 13,
      "heDamage": 57,
      "flashAssists": 0,
      "molotovDamage": 29,
      "ctKills": 4,
      "ctDeaths": 7,
      "tKills": 5,
      "tDeaths": 4,
      "weapons": {
        "mp7": 3,
        "galilar": 1,
        "ak47": 2,
        "hegrenade": 1,
        "knife": 1,
        "m4a1": 1
      },
      "diff": -2,
      "kd": 0.82,
      "hsPercent": 33.33,
      "adr": 70.78,
      "entryRatio": 1,
      "totalClutches": 0,
      "kastPercent": 72.22,
      "impactRating": 0.72,
      "openingDuelWinPercent": 50,
      "firstKillPercent": 5.56,
      "tradeKillPercent": 11.11,
      "ctKd": 0.57,
      "tKd": 1.25,
      "favoriteWeapon": {
        "weapon": "mp7",
        "kills": 3
      },
      "ratingS4N": 0.79,
      "mvpScore": 16.56
    },
    {
      "name": "⑧ ☆ Ludo",
      "steamid": "76561198072925518",
      "team": 2,
      "kills": 11,
      "assists": 4,
      "deaths": 14,
      "headshots": 4,
      "damage": 1049,
      "entryKills": 2,
      "entryDeaths": 3,
      "openingKills": 2,
      "openingDeaths": 3,
      "openingDuels": 5,
      "tradeKills": 3,
      "tradeOpportunities": 0,
      "awpKills": 0,
      "twoKs": 1,
      "threeKs": 1,
      "fourKs": 0,
      "aces": 0,
      "clutch1v1": 0,
      "clutch1v2": 0,
      "clutch1v3": 0,
      "clutch1v4": 0,
      "clutch1v5": 0,
      "baitRounds": 2,
      "kastRounds": 8,
      "heDamage": 111,
      "flashAssists": 0,
      "molotovDamage": 17,
      "ctKills": 5,
      "ctDeaths": 5,
      "tKills": 6,
      "tDeaths": 9,
      "weapons": {
        "deagle": 2,
        "m4a1_silencer": 2,
        "famas": 1,
        "usp_silencer": 1,
        "glock": 1,
        "mac10": 1,
        "ak47": 2,
        "hegrenade": 1
      },
      "diff": -3,
      "kd": 0.79,
      "hsPercent": 36.36,
      "adr": 58.28,
      "entryRatio": 0.67,
      "totalClutches": 0,
      "kastPercent": 44.44,
      "impactRating": 0.83,
      "openingDuelWinPercent": 40,
      "firstKillPercent": 11.11,
      "tradeKillPercent": 27.27,
      "ctKd": 1,
      "tKd": 0.67,
      "favoriteWeapon": {
        "weapon": "deagle",
        "kills": 2
      },
      "ratingS4N": 0.71,
      "mvpScore": 17.58
    },
    {
      "name": "⑧ ☆ kingC.- J",
      "steamid": "76561198810129628",
      "team": 2,
      "kills": 10,
      "assists": 7,
      "deaths": 17,
      "headshots": 4,
      "damage": 1427,
      "entryKills": 1,
      "entryDeaths": 3,
      "openingKills": 1,
      "openingDeaths": 3,
      "openingDuels": 4,
      "tradeKills": 3,
      "tradeOpportunities": 0,
      "awpKills": 3,
      "twoKs": 2,
      "threeKs": 1,
      "fourKs": 0,
      "aces": 0,
      "clutch1v1": 0,
      "clutch1v2": 0,
      "clutch1v3": 0,
      "clutch1v4": 0,
      "clutch1v5": 0,
      "baitRounds": 5,
      "kastRounds": 13,
      "heDamage": 125,
      "flashAssists": 0,
      "molotovDamage": 2,
      "ctKills": 1,
      "ctDeaths": 6,
      "tKills": 9,
      "tDeaths": 11,
      "weapons": {
        "usp_silencer": 1,
        "awp": 3,
        "mp9": 3,
        "deagle": 1,
        "ak47": 1,
        "mac10": 1
      },
      "diff": -7,
      "kd": 0.59,
      "hsPercent": 40,
      "adr": 79.28,
      "entryRatio": 0.33,
      "totalClutches": 0,
      "kastPercent": 72.22,
      "impactRating": 0.94,
      "openingDuelWinPercent": 25,
      "firstKillPercent": 5.56,
      "tradeKillPercent": 30,
      "ctKd": 0.17,
      "tKd": 0.82,
      "favoriteWeapon": {
        "weapon": "awp",
        "kills": 3
      },
      "ratingS4N": 0.66,
      "mvpScore": 15.98
    },
    {
      "name": "⑭ ☆ T0M[1]...:P",
      "steamid": "76561198827102122",
      "team": 2,
      "kills": 10,
      "assists": 3,
      "deaths": 18,
      "headshots": 4,
      "damage": 1157,
      "entryKills": 2,
      "entryDeaths": 3,
      "openingKills": 2,
      "openingDeaths": 3,
      "openingDuels": 5,
      "tradeKills": 3,
      "tradeOpportunities": 0,
      "awpKills": 3,
      "twoKs": 1,
      "threeKs": 0,
      "fourKs": 0,
      "aces": 0,
      "clutch1v1": 0,
      "clutch1v2": 0,
      "clutch1v3": 0,
      "clutch1v4": 0,
      "clutch1v5": 0,
      "baitRounds": 6,
      "kastRounds": 11,
      "heDamage": 51,
      "flashAssists": 0,
      "molotovDamage": 22,
      "ctKills": 1,
      "ctDeaths": 6,
      "tKills": 9,
      "tDeaths": 12,
      "weapons": {
        "elite": 1,
        "m4a1_silencer": 2,
        "famas": 1,
        "awp": 3,
        "p250": 2,
        "ssg08": 1
      },
      "diff": -8,
      "kd": 0.56,
      "hsPercent": 40,
      "adr": 64.28,
      "entryRatio": 0.67,
      "totalClutches": 0,
      "kastPercent": 61.11,
      "impactRating": 0.72,
      "openingDuelWinPercent": 40,
      "firstKillPercent": 11.11,
      "tradeKillPercent": 30,
      "ctKd": 0.17,
      "tKd": 0.75,
      "favoriteWeapon": {
        "weapon": "awp",
        "kills": 3
      },
      "ratingS4N": 0.62,
      "mvpScore": 12.43
    },
    {
      "name": "⑬ santolokura91",
      "steamid": "76561199067681455",
      "team": 2,
      "kills": 8,
      "assists": 1,
      "deaths": 15,
      "headshots": 3,
      "damage": 1008,
      "entryKills": 0,
      "entryDeaths": 3,
      "openingKills": 0,
      "openingDeaths": 3,
      "openingDuels": 3,
      "tradeKills": 2,
      "tradeOpportunities": 0,
      "awpKills": 1,
      "twoKs": 2,
      "threeKs": 1,
      "fourKs": 0,
      "aces": 0,
      "clutch1v1": 0,
      "clutch1v2": 0,
      "clutch1v3": 0,
      "clutch1v4": 0,
      "clutch1v5": 0,
      "baitRounds": 2,
      "kastRounds": 5,
      "heDamage": 81,
      "flashAssists": 0,
      "molotovDamage": 2,
      "ctKills": 1,
      "ctDeaths": 6,
      "tKills": 7,
      "tDeaths": 9,
      "weapons": {
        "m4a1_silencer": 5,
        "usp_silencer": 1,
        "awp": 1,
        "glock": 1
      },
      "diff": -7,
      "kd": 0.53,
      "hsPercent": 37.5,
      "adr": 56,
      "entryRatio": 0,
      "totalClutches": 0,
      "kastPercent": 27.78,
      "impactRating": 0.5,
      "openingDuelWinPercent": 0,
      "firstKillPercent": 0,
      "tradeKillPercent": 25,
      "ctKd": 0.17,
      "tKd": 0.78,
      "favoriteWeapon": {
        "weapon": "m4a1_silencer",
        "kills": 5
      },
      "ratingS4N": 0.53,
      "mvpScore": 6.91
    }
  ],
  "createdAt": "2026-06-10T03:44:45.417Z"
}