{
  "demoFile": "2026-06-29__0248__1__27322785__de_overpass__team-mendona-marlia__vs__team-ludo.dem",
  "map": "de_overpass",
  "server": "Registre-se e jogue @ gamersclub.com.br",
  "officialStartTick": 12316,
  "officialEndTick": 299610,
  "rounds": 42,
  "winnerTeam": 3,
  "teamSummary": [
    {
      "team": 3,
      "kills": 158,
      "deaths": 151,
      "diff": 7
    },
    {
      "team": 2,
      "kills": 151,
      "deaths": 158,
      "diff": -7
    }
  ],
  "mvp": {
    "name": "⑫ ☆ Mendona Marlia",
    "steamid": "76561199171778549",
    "mvpScore": 86.47
  },
  "players": [
    {
      "name": "⑫ ☆ Mendona Marlia",
      "steamid": "76561199171778549",
      "team": 2,
      "kills": 47,
      "assists": 9,
      "deaths": 28,
      "headshots": 29,
      "damage": 4699,
      "entryKills": 6,
      "entryDeaths": 4,
      "openingKills": 6,
      "openingDeaths": 4,
      "openingDuels": 10,
      "tradeKills": 12,
      "tradeOpportunities": 0,
      "awpKills": 7,
      "twoKs": 8,
      "threeKs": 5,
      "fourKs": 1,
      "aces": 0,
      "clutch1v1": 0,
      "clutch1v2": 3,
      "clutch1v3": 0,
      "clutch1v4": 0,
      "clutch1v5": 0,
      "baitRounds": 11,
      "kastRounds": 31,
      "heDamage": 160,
      "flashAssists": 0,
      "molotovDamage": 7,
      "ctKills": 25,
      "ctDeaths": 22,
      "tKills": 22,
      "tDeaths": 6,
      "weapons": {
        "glock": 1,
        "elite": 2,
        "ak47": 31,
        "awp": 7,
        "deagle": 3,
        "m4a1_silencer": 3
      },
      "diff": 19,
      "kd": 1.68,
      "hsPercent": 61.7,
      "adr": 111.88,
      "entryRatio": 1.5,
      "totalClutches": 3,
      "kastPercent": 73.81,
      "impactRating": 1.33,
      "openingDuelWinPercent": 60,
      "firstKillPercent": 14.29,
      "tradeKillPercent": 25.53,
      "ctKd": 1.14,
      "tKd": 3.67,
      "favoriteWeapon": {
        "weapon": "ak47",
        "kills": 31
      },
      "ratingS4N": 1.46,
      "mvpScore": 86.47
    },
    {
      "name": "⑬ ☆ T0M[1]...:P",
      "steamid": "76561198827102122",
      "team": 3,
      "kills": 45,
      "assists": 8,
      "deaths": 29,
      "headshots": 20,
      "damage": 4467,
      "entryKills": 5,
      "entryDeaths": 3,
      "openingKills": 5,
      "openingDeaths": 3,
      "openingDuels": 8,
      "tradeKills": 5,
      "tradeOpportunities": 0,
      "awpKills": 3,
      "twoKs": 11,
      "threeKs": 3,
      "fourKs": 1,
      "aces": 0,
      "clutch1v1": 0,
      "clutch1v2": 1,
      "clutch1v3": 0,
      "clutch1v4": 0,
      "clutch1v5": 0,
      "baitRounds": 10,
      "kastRounds": 36,
      "heDamage": 84,
      "flashAssists": 0,
      "molotovDamage": 82,
      "ctKills": 10,
      "ctDeaths": 10,
      "tKills": 35,
      "tDeaths": 19,
      "weapons": {
        "p250": 2,
        "m4a1_silencer": 12,
        "mp9": 3,
        "tec9": 1,
        "ak47": 22,
        "mac10": 1,
        "m4a1": 1,
        "awp": 3
      },
      "diff": 16,
      "kd": 1.55,
      "hsPercent": 44.44,
      "adr": 106.36,
      "entryRatio": 1.67,
      "totalClutches": 1,
      "kastPercent": 85.71,
      "impactRating": 1.26,
      "openingDuelWinPercent": 62.5,
      "firstKillPercent": 11.9,
      "tradeKillPercent": 11.11,
      "ctKd": 1,
      "tKd": 1.84,
      "favoriteWeapon": {
        "weapon": "ak47",
        "kills": 22
      },
      "ratingS4N": 1.35,
      "mvpScore": 76.85
    },
    {
      "name": "⑧ ☆ Ludo",
      "steamid": "76561198072925518",
      "team": 3,
      "kills": 32,
      "assists": 10,
      "deaths": 27,
      "headshots": 9,
      "damage": 3433,
      "entryKills": 4,
      "entryDeaths": 2,
      "openingKills": 4,
      "openingDeaths": 2,
      "openingDuels": 6,
      "tradeKills": 4,
      "tradeOpportunities": 0,
      "awpKills": 0,
      "twoKs": 3,
      "threeKs": 2,
      "fourKs": 1,
      "aces": 0,
      "clutch1v1": 0,
      "clutch1v2": 1,
      "clutch1v3": 1,
      "clutch1v4": 0,
      "clutch1v5": 0,
      "baitRounds": 5,
      "kastRounds": 32,
      "heDamage": 200,
      "flashAssists": 0,
      "molotovDamage": 7,
      "ctKills": 8,
      "ctDeaths": 7,
      "tKills": 24,
      "tDeaths": 20,
      "weapons": {
        "m4a1": 8,
        "deagle": 4,
        "famas": 1,
        "p250": 3,
        "ak47": 16
      },
      "diff": 5,
      "kd": 1.19,
      "hsPercent": 28.13,
      "adr": 81.74,
      "entryRatio": 2,
      "totalClutches": 2,
      "kastPercent": 76.19,
      "impactRating": 1,
      "openingDuelWinPercent": 66.67,
      "firstKillPercent": 9.52,
      "tradeKillPercent": 12.5,
      "ctKd": 1.14,
      "tKd": 1.2,
      "favoriteWeapon": {
        "weapon": "ak47",
        "kills": 16
      },
      "ratingS4N": 1.07,
      "mvpScore": 55.54
    },
    {
      "name": "⑩ JoT4.",
      "steamid": "76561198392655750",
      "team": 2,
      "kills": 33,
      "assists": 5,
      "deaths": 33,
      "headshots": 16,
      "damage": 3192,
      "entryKills": 8,
      "entryDeaths": 3,
      "openingKills": 8,
      "openingDeaths": 3,
      "openingDuels": 11,
      "tradeKills": 6,
      "tradeOpportunities": 0,
      "awpKills": 0,
      "twoKs": 5,
      "threeKs": 1,
      "fourKs": 0,
      "aces": 0,
      "clutch1v1": 0,
      "clutch1v2": 0,
      "clutch1v3": 0,
      "clutch1v4": 0,
      "clutch1v5": 0,
      "baitRounds": 6,
      "kastRounds": 31,
      "heDamage": 82,
      "flashAssists": 0,
      "molotovDamage": 4,
      "ctKills": 26,
      "ctDeaths": 26,
      "tKills": 7,
      "tDeaths": 7,
      "weapons": {
        "glock": 1,
        "mac10": 2,
        "m4a1": 1,
        "ak47": 13,
        "usp_silencer": 1,
        "m4a1_silencer": 14,
        "mp9": 1
      },
      "diff": 0,
      "kd": 1,
      "hsPercent": 48.48,
      "adr": 76,
      "entryRatio": 2.67,
      "totalClutches": 0,
      "kastPercent": 73.81,
      "impactRating": 0.9,
      "openingDuelWinPercent": 72.73,
      "firstKillPercent": 19.05,
      "tradeKillPercent": 18.18,
      "ctKd": 1,
      "tKd": 1,
      "favoriteWeapon": {
        "weapon": "m4a1_silencer",
        "kills": 14
      },
      "ratingS4N": 1.03,
      "mvpScore": 48.31
    },
    {
      "name": "⑬ ☆ ILUMIN4RI",
      "steamid": "76561199037068708",
      "team": 3,
      "kills": 35,
      "assists": 16,
      "deaths": 31,
      "headshots": 11,
      "damage": 4152,
      "entryKills": 7,
      "entryDeaths": 7,
      "openingKills": 7,
      "openingDeaths": 7,
      "openingDuels": 14,
      "tradeKills": 4,
      "tradeOpportunities": 0,
      "awpKills": 3,
      "twoKs": 7,
      "threeKs": 1,
      "fourKs": 1,
      "aces": 0,
      "clutch1v1": 0,
      "clutch1v2": 0,
      "clutch1v3": 0,
      "clutch1v4": 0,
      "clutch1v5": 0,
      "baitRounds": 5,
      "kastRounds": 30,
      "heDamage": 116,
      "flashAssists": 0,
      "molotovDamage": 53,
      "ctKills": 12,
      "ctDeaths": 11,
      "tKills": 23,
      "tDeaths": 20,
      "weapons": {
        "m4a1": 12,
        "ak47": 15,
        "p90": 1,
        "glock": 1,
        "galilar": 2,
        "hegrenade": 1,
        "awp": 3
      },
      "diff": 4,
      "kd": 1.13,
      "hsPercent": 31.43,
      "adr": 98.86,
      "entryRatio": 1,
      "totalClutches": 0,
      "kastPercent": 71.43,
      "impactRating": 1.21,
      "openingDuelWinPercent": 50,
      "firstKillPercent": 16.67,
      "tradeKillPercent": 11.43,
      "ctKd": 1.09,
      "tKd": 1.15,
      "favoriteWeapon": {
        "weapon": "ak47",
        "kills": 15
      },
      "ratingS4N": 1.03,
      "mvpScore": 59.85
    },
    {
      "name": "⑪ Mende$",
      "steamid": "76561198930446549",
      "team": 2,
      "kills": 27,
      "assists": 12,
      "deaths": 29,
      "headshots": 8,
      "damage": 3188,
      "entryKills": 2,
      "entryDeaths": 4,
      "openingKills": 2,
      "openingDeaths": 4,
      "openingDuels": 6,
      "tradeKills": 4,
      "tradeOpportunities": 0,
      "awpKills": 6,
      "twoKs": 6,
      "threeKs": 0,
      "fourKs": 1,
      "aces": 0,
      "clutch1v1": 0,
      "clutch1v2": 1,
      "clutch1v3": 0,
      "clutch1v4": 0,
      "clutch1v5": 0,
      "baitRounds": 7,
      "kastRounds": 30,
      "heDamage": 22,
      "flashAssists": 2,
      "molotovDamage": 43,
      "ctKills": 19,
      "ctDeaths": 21,
      "tKills": 8,
      "tDeaths": 8,
      "weapons": {
        "galilar": 1,
        "ak47": 10,
        "awp": 6,
        "usp_silencer": 1,
        "m4a1_silencer": 7,
        "m4a1": 2
      },
      "diff": -2,
      "kd": 0.93,
      "hsPercent": 29.63,
      "adr": 75.9,
      "entryRatio": 0.5,
      "totalClutches": 1,
      "kastPercent": 71.43,
      "impactRating": 0.93,
      "openingDuelWinPercent": 33.33,
      "firstKillPercent": 4.76,
      "tradeKillPercent": 14.81,
      "ctKd": 0.9,
      "tKd": 1,
      "favoriteWeapon": {
        "weapon": "ak47",
        "kills": 10
      },
      "ratingS4N": 0.82,
      "mvpScore": 42.01
    },
    {
      "name": "⑦ ☆ kingC.- J",
      "steamid": "76561198810129628",
      "team": 3,
      "kills": 27,
      "assists": 6,
      "deaths": 32,
      "headshots": 5,
      "damage": 2579,
      "entryKills": 5,
      "entryDeaths": 3,
      "openingKills": 5,
      "openingDeaths": 3,
      "openingDuels": 8,
      "tradeKills": 2,
      "tradeOpportunities": 0,
      "awpKills": 15,
      "twoKs": 5,
      "threeKs": 1,
      "fourKs": 0,
      "aces": 0,
      "clutch1v1": 0,
      "clutch1v2": 1,
      "clutch1v3": 0,
      "clutch1v4": 0,
      "clutch1v5": 0,
      "baitRounds": 12,
      "kastRounds": 28,
      "heDamage": 27,
      "flashAssists": 0,
      "molotovDamage": 0,
      "ctKills": 5,
      "ctDeaths": 11,
      "tKills": 22,
      "tDeaths": 21,
      "weapons": {
        "m4a1": 5,
        "awp": 15,
        "mp9": 2,
        "m4a1_silencer": 2,
        "ak47": 3
      },
      "diff": -5,
      "kd": 0.84,
      "hsPercent": 18.52,
      "adr": 61.4,
      "entryRatio": 1.67,
      "totalClutches": 1,
      "kastPercent": 66.67,
      "impactRating": 0.79,
      "openingDuelWinPercent": 62.5,
      "firstKillPercent": 11.9,
      "tradeKillPercent": 7.41,
      "ctKd": 0.45,
      "tKd": 1.05,
      "favoriteWeapon": {
        "weapon": "awp",
        "kills": 15
      },
      "ratingS4N": 0.79,
      "mvpScore": 37.7
    },
    {
      "name": "⑩ Cegol",
      "steamid": "76561197996864918",
      "team": 2,
      "kills": 27,
      "assists": 13,
      "deaths": 35,
      "headshots": 8,
      "damage": 3244,
      "entryKills": 1,
      "entryDeaths": 7,
      "openingKills": 1,
      "openingDeaths": 7,
      "openingDuels": 8,
      "tradeKills": 3,
      "tradeOpportunities": 0,
      "awpKills": 7,
      "twoKs": 5,
      "threeKs": 0,
      "fourKs": 0,
      "aces": 0,
      "clutch1v1": 0,
      "clutch1v2": 1,
      "clutch1v3": 0,
      "clutch1v4": 0,
      "clutch1v5": 0,
      "baitRounds": 10,
      "kastRounds": 32,
      "heDamage": 346,
      "flashAssists": 1,
      "molotovDamage": 35,
      "ctKills": 17,
      "ctDeaths": 25,
      "tKills": 10,
      "tDeaths": 10,
      "weapons": {
        "glock": 3,
        "mac10": 2,
        "ak47": 7,
        "awp": 7,
        "taser": 2,
        "m4a1_silencer": 5,
        "mp9": 1
      },
      "diff": -8,
      "kd": 0.77,
      "hsPercent": 29.63,
      "adr": 77.24,
      "entryRatio": 0.14,
      "totalClutches": 1,
      "kastPercent": 76.19,
      "impactRating": 0.95,
      "openingDuelWinPercent": 12.5,
      "firstKillPercent": 2.38,
      "tradeKillPercent": 11.11,
      "ctKd": 0.68,
      "tKd": 1,
      "favoriteWeapon": {
        "weapon": "ak47",
        "kills": 7
      },
      "ratingS4N": 0.72,
      "mvpScore": 37.26
    },
    {
      "name": "⑦ Nicolas",
      "steamid": "76561199082720391",
      "team": 3,
      "kills": 19,
      "assists": 9,
      "deaths": 32,
      "headshots": 9,
      "damage": 2612,
      "entryKills": 3,
      "entryDeaths": 3,
      "openingKills": 3,
      "openingDeaths": 3,
      "openingDuels": 6,
      "tradeKills": 6,
      "tradeOpportunities": 0,
      "awpKills": 0,
      "twoKs": 3,
      "threeKs": 0,
      "fourKs": 0,
      "aces": 0,
      "clutch1v1": 0,
      "clutch1v2": 1,
      "clutch1v3": 0,
      "clutch1v4": 0,
      "clutch1v5": 0,
      "baitRounds": 8,
      "kastRounds": 30,
      "heDamage": 138,
      "flashAssists": 0,
      "molotovDamage": 9,
      "ctKills": 5,
      "ctDeaths": 10,
      "tKills": 14,
      "tDeaths": 22,
      "weapons": {
        "usp_silencer_off": 1,
        "m4a1": 8,
        "m4a1_silencer": 2,
        "galilar": 1,
        "ak47": 7
      },
      "diff": -13,
      "kd": 0.59,
      "hsPercent": 47.37,
      "adr": 62.19,
      "entryRatio": 1,
      "totalClutches": 1,
      "kastPercent": 71.43,
      "impactRating": 0.67,
      "openingDuelWinPercent": 50,
      "firstKillPercent": 7.14,
      "tradeKillPercent": 31.58,
      "ctKd": 0.5,
      "tKd": 0.64,
      "favoriteWeapon": {
        "weapon": "m4a1",
        "kills": 8
      },
      "ratingS4N": 0.67,
      "mvpScore": 23.21
    },
    {
      "name": "⑥ mendiZADA",
      "steamid": "76561198415487421",
      "team": 2,
      "kills": 17,
      "assists": 8,
      "deaths": 33,
      "headshots": 11,
      "damage": 2127,
      "entryKills": 1,
      "entryDeaths": 6,
      "openingKills": 1,
      "openingDeaths": 6,
      "openingDuels": 7,
      "tradeKills": 0,
      "tradeOpportunities": 0,
      "awpKills": 0,
      "twoKs": 3,
      "threeKs": 1,
      "fourKs": 0,
      "aces": 0,
      "clutch1v1": 0,
      "clutch1v2": 0,
      "clutch1v3": 0,
      "clutch1v4": 0,
      "clutch1v5": 0,
      "baitRounds": 7,
      "kastRounds": 21,
      "heDamage": 6,
      "flashAssists": 0,
      "molotovDamage": 0,
      "ctKills": 15,
      "ctDeaths": 24,
      "tKills": 2,
      "tDeaths": 9,
      "weapons": {
        "ak47": 9,
        "usp_silencer": 2,
        "m4a1": 5,
        "mp9": 1
      },
      "diff": -16,
      "kd": 0.52,
      "hsPercent": 64.71,
      "adr": 50.64,
      "entryRatio": 0.17,
      "totalClutches": 0,
      "kastPercent": 50,
      "impactRating": 0.6,
      "openingDuelWinPercent": 14.29,
      "firstKillPercent": 2.38,
      "tradeKillPercent": 0,
      "ctKd": 0.63,
      "tKd": 0.22,
      "favoriteWeapon": {
        "weapon": "ak47",
        "kills": 9
      },
      "ratingS4N": 0.57,
      "mvpScore": 13.7
    }
  ],
  "createdAt": "2026-06-29T14:46:15.477Z"
}