{
  "demoFile": "2026-06-08__0229__1__27148312__de_dust2__team-chzin__vs__team-kingc-j.dem",
  "map": "de_dust2",
  "server": "Registre-se e jogue @ gamersclub.com.br",
  "officialStartTick": 12164,
  "officialEndTick": 245994,
  "rounds": 36,
  "winnerTeam": 2,
  "teamSummary": [
    {
      "team": 2,
      "kills": 134,
      "deaths": 119,
      "diff": 15
    },
    {
      "team": 3,
      "kills": 119,
      "deaths": 134,
      "diff": -15
    }
  ],
  "mvp": {
    "name": "⑭ ☆ T0M[1]...:P",
    "steamid": "76561198827102122",
    "mvpScore": 73.28
  },
  "players": [
    {
      "name": "⑭ ☆ T0M[1]...:P",
      "steamid": "76561198827102122",
      "team": 2,
      "kills": 37,
      "assists": 12,
      "deaths": 21,
      "headshots": 6,
      "damage": 4357,
      "entryKills": 8,
      "entryDeaths": 5,
      "openingKills": 8,
      "openingDeaths": 5,
      "openingDuels": 13,
      "tradeKills": 4,
      "tradeOpportunities": 0,
      "awpKills": 18,
      "twoKs": 6,
      "threeKs": 0,
      "fourKs": 2,
      "aces": 1,
      "clutch1v1": 0,
      "clutch1v2": 1,
      "clutch1v3": 0,
      "clutch1v4": 0,
      "clutch1v5": 0,
      "baitRounds": 8,
      "kastRounds": 26,
      "heDamage": 223,
      "flashAssists": 0,
      "molotovDamage": 11,
      "ctKills": 24,
      "ctDeaths": 16,
      "tKills": 13,
      "tDeaths": 5,
      "weapons": {
        "ssg08": 2,
        "ak47": 8,
        "awp": 18,
        "m4a1_silencer": 7,
        "glock": 2
      },
      "diff": 16,
      "kd": 1.76,
      "hsPercent": 16.22,
      "adr": 121.03,
      "entryRatio": 1.6,
      "totalClutches": 1,
      "kastPercent": 72.22,
      "impactRating": 1.36,
      "openingDuelWinPercent": 61.54,
      "firstKillPercent": 22.22,
      "tradeKillPercent": 10.81,
      "ctKd": 1.5,
      "tKd": 2.6,
      "favoriteWeapon": {
        "weapon": "awp",
        "kills": 18
      },
      "ratingS4N": 1.45,
      "mvpScore": 73.28
    },
    {
      "name": "⑬ ILUMIN4RI",
      "steamid": "76561199037068708",
      "team": 2,
      "kills": 28,
      "assists": 8,
      "deaths": 22,
      "headshots": 12,
      "damage": 2743,
      "entryKills": 3,
      "entryDeaths": 1,
      "openingKills": 3,
      "openingDeaths": 1,
      "openingDuels": 4,
      "tradeKills": 10,
      "tradeOpportunities": 0,
      "awpKills": 0,
      "twoKs": 5,
      "threeKs": 1,
      "fourKs": 0,
      "aces": 0,
      "clutch1v1": 0,
      "clutch1v2": 1,
      "clutch1v3": 0,
      "clutch1v4": 0,
      "clutch1v5": 0,
      "baitRounds": 5,
      "kastRounds": 29,
      "heDamage": 204,
      "flashAssists": 1,
      "molotovDamage": 1,
      "ctKills": 18,
      "ctDeaths": 14,
      "tKills": 10,
      "tDeaths": 8,
      "weapons": {
        "elite": 1,
        "mp9": 3,
        "ak47": 12,
        "m4a1_silencer": 2,
        "m4a1": 4,
        "glock": 2,
        "galilar": 2,
        "mac10": 2
      },
      "diff": 6,
      "kd": 1.27,
      "hsPercent": 42.86,
      "adr": 76.19,
      "entryRatio": 3,
      "totalClutches": 1,
      "kastPercent": 80.56,
      "impactRating": 1,
      "openingDuelWinPercent": 75,
      "firstKillPercent": 8.33,
      "tradeKillPercent": 35.71,
      "ctKd": 1.29,
      "tKd": 1.25,
      "favoriteWeapon": {
        "weapon": "ak47",
        "kills": 12
      },
      "ratingS4N": 1.19,
      "mvpScore": 48.6
    },
    {
      "name": "⑧ ☆ kingC.- J",
      "steamid": "76561198810129628",
      "team": 2,
      "kills": 28,
      "assists": 6,
      "deaths": 25,
      "headshots": 11,
      "damage": 2969,
      "entryKills": 2,
      "entryDeaths": 3,
      "openingKills": 2,
      "openingDeaths": 3,
      "openingDuels": 5,
      "tradeKills": 2,
      "tradeOpportunities": 0,
      "awpKills": 8,
      "twoKs": 7,
      "threeKs": 1,
      "fourKs": 0,
      "aces": 0,
      "clutch1v1": 0,
      "clutch1v2": 0,
      "clutch1v3": 0,
      "clutch1v4": 0,
      "clutch1v5": 0,
      "baitRounds": 10,
      "kastRounds": 25,
      "heDamage": 37,
      "flashAssists": 0,
      "molotovDamage": 13,
      "ctKills": 19,
      "ctDeaths": 18,
      "tKills": 9,
      "tDeaths": 7,
      "weapons": {
        "usp_silencer": 1,
        "mp9": 1,
        "ak47": 12,
        "fiveseven": 1,
        "m4a1_silencer": 2,
        "awp": 8,
        "mac10": 1,
        "galilar": 1,
        "deagle": 1
      },
      "diff": 3,
      "kd": 1.12,
      "hsPercent": 39.29,
      "adr": 82.47,
      "entryRatio": 0.67,
      "totalClutches": 0,
      "kastPercent": 69.44,
      "impactRating": 0.94,
      "openingDuelWinPercent": 40,
      "firstKillPercent": 5.56,
      "tradeKillPercent": 7.14,
      "ctKd": 1.06,
      "tKd": 1.29,
      "favoriteWeapon": {
        "weapon": "ak47",
        "kills": 12
      },
      "ratingS4N": 0.97,
      "mvpScore": 42.19
    },
    {
      "name": "⑪ ✓ GORDINHO",
      "steamid": "76561199361370322",
      "team": 3,
      "kills": 27,
      "assists": 7,
      "deaths": 28,
      "headshots": 7,
      "damage": 2843,
      "entryKills": 7,
      "entryDeaths": 3,
      "openingKills": 7,
      "openingDeaths": 3,
      "openingDuels": 10,
      "tradeKills": 2,
      "tradeOpportunities": 0,
      "awpKills": 2,
      "twoKs": 8,
      "threeKs": 1,
      "fourKs": 0,
      "aces": 0,
      "clutch1v1": 0,
      "clutch1v2": 0,
      "clutch1v3": 0,
      "clutch1v4": 0,
      "clutch1v5": 0,
      "baitRounds": 5,
      "kastRounds": 25,
      "heDamage": 62,
      "flashAssists": 1,
      "molotovDamage": 45,
      "ctKills": 6,
      "ctDeaths": 8,
      "tKills": 21,
      "tDeaths": 20,
      "weapons": {
        "ak47": 10,
        "fiveseven": 1,
        "usp_silencer": 1,
        "m4a1": 10,
        "m4a1_silencer": 3,
        "awp": 2
      },
      "diff": -1,
      "kd": 0.96,
      "hsPercent": 25.93,
      "adr": 78.97,
      "entryRatio": 2.33,
      "totalClutches": 0,
      "kastPercent": 69.44,
      "impactRating": 0.94,
      "openingDuelWinPercent": 70,
      "firstKillPercent": 19.44,
      "tradeKillPercent": 7.41,
      "ctKd": 0.75,
      "tKd": 1.05,
      "favoriteWeapon": {
        "weapon": "ak47",
        "kills": 10
      },
      "ratingS4N": 0.96,
      "mvpScore": 41.89
    },
    {
      "name": "⑧ ✓ ★ chzin",
      "steamid": "76561199334527619",
      "team": 3,
      "kills": 25,
      "assists": 3,
      "deaths": 24,
      "headshots": 10,
      "damage": 2261,
      "entryKills": 2,
      "entryDeaths": 2,
      "openingKills": 2,
      "openingDeaths": 2,
      "openingDuels": 4,
      "tradeKills": 10,
      "tradeOpportunities": 0,
      "awpKills": 7,
      "twoKs": 5,
      "threeKs": 0,
      "fourKs": 0,
      "aces": 0,
      "clutch1v1": 0,
      "clutch1v2": 2,
      "clutch1v3": 0,
      "clutch1v4": 0,
      "clutch1v5": 0,
      "baitRounds": 10,
      "kastRounds": 21,
      "heDamage": 81,
      "flashAssists": 1,
      "molotovDamage": 1,
      "ctKills": 8,
      "ctDeaths": 8,
      "tKills": 17,
      "tDeaths": 16,
      "weapons": {
        "glock": 1,
        "usp_silencer": 1,
        "p250": 1,
        "ak47": 11,
        "awp": 7,
        "m4a1": 3,
        "m4a1_silencer": 1
      },
      "diff": 1,
      "kd": 1.04,
      "hsPercent": 40,
      "adr": 62.81,
      "entryRatio": 1,
      "totalClutches": 2,
      "kastPercent": 58.33,
      "impactRating": 0.78,
      "openingDuelWinPercent": 50,
      "firstKillPercent": 5.56,
      "tradeKillPercent": 40,
      "ctKd": 1,
      "tKd": 1.06,
      "favoriteWeapon": {
        "weapon": "ak47",
        "kills": 11
      },
      "ratingS4N": 0.9,
      "mvpScore": 38.67
    },
    {
      "name": "⑨ ✓ G u G x",
      "steamid": "76561199866441251",
      "team": 3,
      "kills": 20,
      "assists": 8,
      "deaths": 28,
      "headshots": 10,
      "damage": 2380,
      "entryKills": 3,
      "entryDeaths": 1,
      "openingKills": 3,
      "openingDeaths": 1,
      "openingDuels": 4,
      "tradeKills": 2,
      "tradeOpportunities": 0,
      "awpKills": 0,
      "twoKs": 4,
      "threeKs": 1,
      "fourKs": 0,
      "aces": 0,
      "clutch1v1": 0,
      "clutch1v2": 0,
      "clutch1v3": 0,
      "clutch1v4": 0,
      "clutch1v5": 0,
      "baitRounds": 9,
      "kastRounds": 23,
      "heDamage": 6,
      "flashAssists": 1,
      "molotovDamage": 4,
      "ctKills": 9,
      "ctDeaths": 9,
      "tKills": 11,
      "tDeaths": 19,
      "weapons": {
        "glock": 2,
        "ak47": 12,
        "usp_silencer": 1,
        "m4a1": 5
      },
      "diff": -8,
      "kd": 0.71,
      "hsPercent": 50,
      "adr": 66.11,
      "entryRatio": 3,
      "totalClutches": 0,
      "kastPercent": 63.89,
      "impactRating": 0.78,
      "openingDuelWinPercent": 75,
      "firstKillPercent": 8.33,
      "tradeKillPercent": 10,
      "ctKd": 1,
      "tKd": 0.58,
      "favoriteWeapon": {
        "weapon": "ak47",
        "kills": 12
      },
      "ratingS4N": 0.88,
      "mvpScore": 25.93
    },
    {
      "name": "⑩ ★ Limp Bizkit",
      "steamid": "76561199504824937",
      "team": 3,
      "kills": 23,
      "assists": 11,
      "deaths": 27,
      "headshots": 12,
      "damage": 2801,
      "entryKills": 5,
      "entryDeaths": 8,
      "openingKills": 5,
      "openingDeaths": 8,
      "openingDuels": 13,
      "tradeKills": 2,
      "tradeOpportunities": 0,
      "awpKills": 3,
      "twoKs": 6,
      "threeKs": 1,
      "fourKs": 1,
      "aces": 0,
      "clutch1v1": 0,
      "clutch1v2": 1,
      "clutch1v3": 0,
      "clutch1v4": 0,
      "clutch1v5": 0,
      "baitRounds": 2,
      "kastRounds": 20,
      "heDamage": 125,
      "flashAssists": 1,
      "molotovDamage": 27,
      "ctKills": 4,
      "ctDeaths": 10,
      "tKills": 19,
      "tDeaths": 17,
      "weapons": {
        "ak47": 13,
        "ssg08": 2,
        "m4a1_silencer": 5,
        "awp": 3
      },
      "diff": -4,
      "kd": 0.85,
      "hsPercent": 52.17,
      "adr": 77.81,
      "entryRatio": 0.63,
      "totalClutches": 1,
      "kastPercent": 55.56,
      "impactRating": 0.94,
      "openingDuelWinPercent": 38.46,
      "firstKillPercent": 13.89,
      "tradeKillPercent": 8.7,
      "ctKd": 0.4,
      "tKd": 1.12,
      "favoriteWeapon": {
        "weapon": "ak47",
        "kills": 13
      },
      "ratingS4N": 0.84,
      "mvpScore": 37.63
    },
    {
      "name": "⑪ ✓ ☆ Wwchagas181",
      "steamid": "76561198875443324",
      "team": 3,
      "kills": 24,
      "assists": 7,
      "deaths": 27,
      "headshots": 9,
      "damage": 2808,
      "entryKills": 2,
      "entryDeaths": 3,
      "openingKills": 2,
      "openingDeaths": 3,
      "openingDuels": 5,
      "tradeKills": 5,
      "tradeOpportunities": 0,
      "awpKills": 0,
      "twoKs": 5,
      "threeKs": 1,
      "fourKs": 0,
      "aces": 0,
      "clutch1v1": 0,
      "clutch1v2": 0,
      "clutch1v3": 0,
      "clutch1v4": 0,
      "clutch1v5": 0,
      "baitRounds": 8,
      "kastRounds": 25,
      "heDamage": 54,
      "flashAssists": 0,
      "molotovDamage": 0,
      "ctKills": 9,
      "ctDeaths": 8,
      "tKills": 15,
      "tDeaths": 19,
      "weapons": {
        "glock": 1,
        "tec9": 1,
        "p250": 1,
        "ak47": 12,
        "m4a1": 9
      },
      "diff": -3,
      "kd": 0.89,
      "hsPercent": 37.5,
      "adr": 78,
      "entryRatio": 0.67,
      "totalClutches": 0,
      "kastPercent": 69.44,
      "impactRating": 0.86,
      "openingDuelWinPercent": 40,
      "firstKillPercent": 5.56,
      "tradeKillPercent": 20.83,
      "ctKd": 1.13,
      "tKd": 0.79,
      "favoriteWeapon": {
        "weapon": "ak47",
        "kills": 12
      },
      "ratingS4N": 0.83,
      "mvpScore": 33.51
    },
    {
      "name": "⑧ ☆ Ludo",
      "steamid": "76561198072925518",
      "team": 2,
      "kills": 21,
      "assists": 6,
      "deaths": 23,
      "headshots": 9,
      "damage": 2339,
      "entryKills": 1,
      "entryDeaths": 5,
      "openingKills": 1,
      "openingDeaths": 5,
      "openingDuels": 6,
      "tradeKills": 3,
      "tradeOpportunities": 0,
      "awpKills": 0,
      "twoKs": 3,
      "threeKs": 1,
      "fourKs": 0,
      "aces": 0,
      "clutch1v1": 0,
      "clutch1v2": 0,
      "clutch1v3": 0,
      "clutch1v4": 0,
      "clutch1v5": 0,
      "baitRounds": 1,
      "kastRounds": 26,
      "heDamage": 113,
      "flashAssists": 0,
      "molotovDamage": 0,
      "ctKills": 18,
      "ctDeaths": 17,
      "tKills": 3,
      "tDeaths": 6,
      "weapons": {
        "usp_silencer": 1,
        "mp9": 1,
        "m4a1_silencer": 5,
        "glock": 1,
        "ak47": 10,
        "m4a1": 3
      },
      "diff": -2,
      "kd": 0.91,
      "hsPercent": 42.86,
      "adr": 64.97,
      "entryRatio": 0.2,
      "totalClutches": 0,
      "kastPercent": 72.22,
      "impactRating": 0.75,
      "openingDuelWinPercent": 16.67,
      "firstKillPercent": 2.78,
      "tradeKillPercent": 14.29,
      "ctKd": 1.06,
      "tKd": 0.5,
      "favoriteWeapon": {
        "weapon": "ak47",
        "kills": 10
      },
      "ratingS4N": 0.78,
      "mvpScore": 29.47
    },
    {
      "name": "⑧ Nicolas",
      "steamid": "76561199082720391",
      "team": 2,
      "kills": 20,
      "assists": 11,
      "deaths": 28,
      "headshots": 8,
      "damage": 2331,
      "entryKills": 3,
      "entryDeaths": 5,
      "openingKills": 3,
      "openingDeaths": 5,
      "openingDuels": 8,
      "tradeKills": 1,
      "tradeOpportunities": 0,
      "awpKills": 1,
      "twoKs": 1,
      "threeKs": 1,
      "fourKs": 0,
      "aces": 0,
      "clutch1v1": 0,
      "clutch1v2": 0,
      "clutch1v3": 0,
      "clutch1v4": 0,
      "clutch1v5": 0,
      "baitRounds": 9,
      "kastRounds": 26,
      "heDamage": 192,
      "flashAssists": 0,
      "molotovDamage": 45,
      "ctKills": 12,
      "ctDeaths": 18,
      "tKills": 8,
      "tDeaths": 10,
      "weapons": {
        "mp9": 2,
        "m4a1_silencer": 5,
        "m4a1": 2,
        "famas": 1,
        "galilar": 1,
        "awp": 1,
        "ak47": 7,
        "hegrenade": 1
      },
      "diff": -8,
      "kd": 0.71,
      "hsPercent": 40,
      "adr": 64.75,
      "entryRatio": 0.6,
      "totalClutches": 0,
      "kastPercent": 72.22,
      "impactRating": 0.86,
      "openingDuelWinPercent": 37.5,
      "firstKillPercent": 8.33,
      "tradeKillPercent": 5,
      "ctKd": 0.67,
      "tKd": 0.8,
      "favoriteWeapon": {
        "weapon": "ak47",
        "kills": 7
      },
      "ratingS4N": 0.7,
      "mvpScore": 27.89
    }
  ],
  "createdAt": "2026-06-10T03:44:13.137Z"
}