{
  "demoFile": "2026-06-07__0311__1__27137047__de_overpass__team-bezin__vs__team-t0m1-p.dem",
  "map": "de_overpass",
  "server": "Registre-se e jogue @ gamersclub.com.br",
  "officialStartTick": 11623,
  "officialEndTick": 130836,
  "rounds": 20,
  "winnerTeam": 2,
  "teamSummary": [
    {
      "team": 2,
      "kills": 84,
      "deaths": 65,
      "diff": 19
    },
    {
      "team": 3,
      "kills": 65,
      "deaths": 84,
      "diff": -19
    }
  ],
  "mvp": {
    "name": "⑥ ✓ AWP_Moreno",
    "steamid": "76561198843017916",
    "mvpScore": 46.14
  },
  "players": [
    {
      "name": "⑥ ✓ AWP_Moreno",
      "steamid": "76561198843017916",
      "team": 2,
      "kills": 23,
      "assists": 5,
      "deaths": 13,
      "headshots": 9,
      "damage": 1961,
      "entryKills": 4,
      "entryDeaths": 0,
      "openingKills": 4,
      "openingDeaths": 0,
      "openingDuels": 4,
      "tradeKills": 3,
      "tradeOpportunities": 0,
      "awpKills": 3,
      "twoKs": 5,
      "threeKs": 2,
      "fourKs": 0,
      "aces": 0,
      "clutch1v1": 0,
      "clutch1v2": 0,
      "clutch1v3": 0,
      "clutch1v4": 0,
      "clutch1v5": 0,
      "baitRounds": 3,
      "kastRounds": 18,
      "heDamage": 0,
      "flashAssists": 0,
      "molotovDamage": 0,
      "ctKills": 8,
      "ctDeaths": 6,
      "tKills": 15,
      "tDeaths": 7,
      "weapons": {
        "usp_silencer": 2,
        "m4a1": 7,
        "ak47": 8,
        "awp": 3,
        "glock": 2,
        "cz75a": 1
      },
      "diff": 10,
      "kd": 1.77,
      "hsPercent": 39.13,
      "adr": 98.05,
      "entryRatio": 4,
      "totalClutches": 0,
      "kastPercent": 90,
      "impactRating": 1.4,
      "openingDuelWinPercent": 100,
      "firstKillPercent": 20,
      "tradeKillPercent": 13.04,
      "ctKd": 1.33,
      "tKd": 2.14,
      "favoriteWeapon": {
        "weapon": "ak47",
        "kills": 8
      },
      "ratingS4N": 1.57,
      "mvpScore": 46.14
    },
    {
      "name": "⑨ drekb",
      "steamid": "76561198082095427",
      "team": 2,
      "kills": 20,
      "assists": 2,
      "deaths": 14,
      "headshots": 11,
      "damage": 2075,
      "entryKills": 3,
      "entryDeaths": 3,
      "openingKills": 3,
      "openingDeaths": 3,
      "openingDuels": 6,
      "tradeKills": 1,
      "tradeOpportunities": 0,
      "awpKills": 0,
      "twoKs": 4,
      "threeKs": 0,
      "fourKs": 1,
      "aces": 0,
      "clutch1v1": 0,
      "clutch1v2": 0,
      "clutch1v3": 0,
      "clutch1v4": 0,
      "clutch1v5": 0,
      "baitRounds": 5,
      "kastRounds": 17,
      "heDamage": 134,
      "flashAssists": 0,
      "molotovDamage": 34,
      "ctKills": 8,
      "ctDeaths": 5,
      "tKills": 12,
      "tDeaths": 9,
      "weapons": {
        "usp_silencer": 2,
        "m4a1": 9,
        "hegrenade": 1,
        "glock": 1,
        "tec9": 5,
        "knife_cord": 1,
        "m4a1_silencer": 1
      },
      "diff": 6,
      "kd": 1.43,
      "hsPercent": 55,
      "adr": 103.75,
      "entryRatio": 1,
      "totalClutches": 0,
      "kastPercent": 85,
      "impactRating": 1.1,
      "openingDuelWinPercent": 50,
      "firstKillPercent": 15,
      "tradeKillPercent": 5,
      "ctKd": 1.6,
      "tKd": 1.33,
      "favoriteWeapon": {
        "weapon": "m4a1",
        "kills": 9
      },
      "ratingS4N": 1.25,
      "mvpScore": 36.86
    },
    {
      "name": "⑨ Basu",
      "steamid": "76561198087755900",
      "team": 3,
      "kills": 20,
      "assists": 5,
      "deaths": 15,
      "headshots": 4,
      "damage": 2430,
      "entryKills": 1,
      "entryDeaths": 2,
      "openingKills": 1,
      "openingDeaths": 2,
      "openingDuels": 3,
      "tradeKills": 6,
      "tradeOpportunities": 0,
      "awpKills": 0,
      "twoKs": 3,
      "threeKs": 2,
      "fourKs": 0,
      "aces": 0,
      "clutch1v1": 0,
      "clutch1v2": 0,
      "clutch1v3": 1,
      "clutch1v4": 0,
      "clutch1v5": 0,
      "baitRounds": 3,
      "kastRounds": 14,
      "heDamage": 62,
      "flashAssists": 0,
      "molotovDamage": 0,
      "ctKills": 10,
      "ctDeaths": 9,
      "tKills": 10,
      "tDeaths": 6,
      "weapons": {
        "tec9": 1,
        "galilar": 5,
        "deagle": 2,
        "ak47": 2,
        "mp7": 8,
        "m4a1": 1,
        "p90": 1
      },
      "diff": 5,
      "kd": 1.33,
      "hsPercent": 20,
      "adr": 121.5,
      "entryRatio": 0.5,
      "totalClutches": 1,
      "kastPercent": 70,
      "impactRating": 1.25,
      "openingDuelWinPercent": 33.33,
      "firstKillPercent": 5,
      "tradeKillPercent": 30,
      "ctKd": 1.11,
      "tKd": 1.67,
      "favoriteWeapon": {
        "weapon": "mp7",
        "kills": 8
      },
      "ratingS4N": 1.17,
      "mvpScore": 38.7
    },
    {
      "name": "⑩ ☆ bezin",
      "steamid": "76561198233012548",
      "team": 2,
      "kills": 16,
      "assists": 3,
      "deaths": 12,
      "headshots": 10,
      "damage": 1474,
      "entryKills": 1,
      "entryDeaths": 0,
      "openingKills": 1,
      "openingDeaths": 0,
      "openingDuels": 1,
      "tradeKills": 6,
      "tradeOpportunities": 0,
      "awpKills": 0,
      "twoKs": 1,
      "threeKs": 0,
      "fourKs": 0,
      "aces": 1,
      "clutch1v1": 0,
      "clutch1v2": 1,
      "clutch1v3": 0,
      "clutch1v4": 0,
      "clutch1v5": 0,
      "baitRounds": 1,
      "kastRounds": 14,
      "heDamage": 33,
      "flashAssists": 0,
      "molotovDamage": 0,
      "ctKills": 8,
      "ctDeaths": 4,
      "tKills": 8,
      "tDeaths": 8,
      "weapons": {
        "deagle": 1,
        "m4a1": 7,
        "glock": 1,
        "ak47": 7
      },
      "diff": 4,
      "kd": 1.33,
      "hsPercent": 62.5,
      "adr": 73.7,
      "entryRatio": 1,
      "totalClutches": 1,
      "kastPercent": 70,
      "impactRating": 0.95,
      "openingDuelWinPercent": 100,
      "firstKillPercent": 5,
      "tradeKillPercent": 37.5,
      "ctKd": 2,
      "tKd": 1,
      "favoriteWeapon": {
        "weapon": "m4a1",
        "kills": 7
      },
      "ratingS4N": 1.13,
      "mvpScore": 30.56
    },
    {
      "name": "⑬ ✓ ★ Danilo",
      "steamid": "76561198311965835",
      "team": 2,
      "kills": 13,
      "assists": 6,
      "deaths": 14,
      "headshots": 6,
      "damage": 1748,
      "entryKills": 3,
      "entryDeaths": 3,
      "openingKills": 3,
      "openingDeaths": 3,
      "openingDuels": 6,
      "tradeKills": 2,
      "tradeOpportunities": 0,
      "awpKills": 0,
      "twoKs": 2,
      "threeKs": 1,
      "fourKs": 0,
      "aces": 0,
      "clutch1v1": 0,
      "clutch1v2": 1,
      "clutch1v3": 0,
      "clutch1v4": 0,
      "clutch1v5": 0,
      "baitRounds": 6,
      "kastRounds": 17,
      "heDamage": 3,
      "flashAssists": 0,
      "molotovDamage": 0,
      "ctKills": 5,
      "ctDeaths": 5,
      "tKills": 8,
      "tDeaths": 9,
      "weapons": {
        "m4a1": 7,
        "famas": 1,
        "mac10": 1,
        "tec9": 1,
        "m4a1_silencer": 1,
        "ak47": 2
      },
      "diff": -1,
      "kd": 0.93,
      "hsPercent": 46.15,
      "adr": 87.4,
      "entryRatio": 1,
      "totalClutches": 1,
      "kastPercent": 85,
      "impactRating": 0.95,
      "openingDuelWinPercent": 50,
      "firstKillPercent": 15,
      "tradeKillPercent": 15.38,
      "ctKd": 1,
      "tKd": 0.89,
      "favoriteWeapon": {
        "weapon": "m4a1",
        "kills": 7
      },
      "ratingS4N": 0.93,
      "mvpScore": 27.32
    },
    {
      "name": "⓪ KNN Joaquim DasAWPslt; Nabuco",
      "steamid": "76561198342796076",
      "team": 2,
      "kills": 12,
      "assists": 6,
      "deaths": 12,
      "headshots": 4,
      "damage": 1515,
      "entryKills": 1,
      "entryDeaths": 2,
      "openingKills": 1,
      "openingDeaths": 2,
      "openingDuels": 3,
      "tradeKills": 3,
      "tradeOpportunities": 0,
      "awpKills": 5,
      "twoKs": 5,
      "threeKs": 0,
      "fourKs": 0,
      "aces": 0,
      "clutch1v1": 0,
      "clutch1v2": 0,
      "clutch1v3": 0,
      "clutch1v4": 0,
      "clutch1v5": 0,
      "baitRounds": 3,
      "kastRounds": 15,
      "heDamage": 31,
      "flashAssists": 0,
      "molotovDamage": 0,
      "ctKills": 5,
      "ctDeaths": 5,
      "tKills": 7,
      "tDeaths": 7,
      "weapons": {
        "m4a1_silencer": 2,
        "awp": 5,
        "glock": 1,
        "elite": 1,
        "ak47": 3
      },
      "diff": 0,
      "kd": 1,
      "hsPercent": 33.33,
      "adr": 75.75,
      "entryRatio": 0.5,
      "totalClutches": 0,
      "kastPercent": 75,
      "impactRating": 0.9,
      "openingDuelWinPercent": 33.33,
      "firstKillPercent": 5,
      "tradeKillPercent": 25,
      "ctKd": 1,
      "tKd": 1,
      "favoriteWeapon": {
        "weapon": "awp",
        "kills": 5
      },
      "ratingS4N": 0.86,
      "mvpScore": 22.92
    },
    {
      "name": "⑭ ☆ MOU /L",
      "steamid": "76561198149518655",
      "team": 3,
      "kills": 13,
      "assists": 2,
      "deaths": 18,
      "headshots": 7,
      "damage": 1281,
      "entryKills": 3,
      "entryDeaths": 2,
      "openingKills": 3,
      "openingDeaths": 2,
      "openingDuels": 5,
      "tradeKills": 3,
      "tradeOpportunities": 0,
      "awpKills": 0,
      "twoKs": 2,
      "threeKs": 1,
      "fourKs": 0,
      "aces": 0,
      "clutch1v1": 0,
      "clutch1v2": 0,
      "clutch1v3": 0,
      "clutch1v4": 0,
      "clutch1v5": 0,
      "baitRounds": 1,
      "kastRounds": 14,
      "heDamage": 122,
      "flashAssists": 0,
      "molotovDamage": 0,
      "ctKills": 9,
      "ctDeaths": 11,
      "tKills": 4,
      "tDeaths": 7,
      "weapons": {
        "glock": 3,
        "galilar": 2,
        "ak47": 3,
        "cz75a": 1,
        "usp_silencer": 1,
        "famas": 3
      },
      "diff": -5,
      "kd": 0.72,
      "hsPercent": 53.85,
      "adr": 64.05,
      "entryRatio": 1.5,
      "totalClutches": 0,
      "kastPercent": 70,
      "impactRating": 0.75,
      "openingDuelWinPercent": 60,
      "firstKillPercent": 15,
      "tradeKillPercent": 23.08,
      "ctKd": 0.82,
      "tKd": 0.57,
      "favoriteWeapon": {
        "weapon": "glock",
        "kills": 3
      },
      "ratingS4N": 0.79,
      "mvpScore": 18.37
    },
    {
      "name": "⑭ ☆ T0M[1]...:P",
      "steamid": "76561198827102122",
      "team": 3,
      "kills": 11,
      "assists": 4,
      "deaths": 17,
      "headshots": 5,
      "damage": 1359,
      "entryKills": 2,
      "entryDeaths": 3,
      "openingKills": 2,
      "openingDeaths": 3,
      "openingDuels": 5,
      "tradeKills": 1,
      "tradeOpportunities": 0,
      "awpKills": 2,
      "twoKs": 4,
      "threeKs": 0,
      "fourKs": 0,
      "aces": 0,
      "clutch1v1": 0,
      "clutch1v2": 1,
      "clutch1v3": 0,
      "clutch1v4": 0,
      "clutch1v5": 0,
      "baitRounds": 7,
      "kastRounds": 11,
      "heDamage": 0,
      "flashAssists": 0,
      "molotovDamage": 0,
      "ctKills": 8,
      "ctDeaths": 10,
      "tKills": 3,
      "tDeaths": 7,
      "weapons": {
        "glock": 1,
        "ak47": 4,
        "ssg08": 1,
        "awp": 2,
        "usp_silencer": 1,
        "tec9": 1,
        "mp9": 1
      },
      "diff": -6,
      "kd": 0.65,
      "hsPercent": 45.45,
      "adr": 67.95,
      "entryRatio": 0.67,
      "totalClutches": 1,
      "kastPercent": 55,
      "impactRating": 0.75,
      "openingDuelWinPercent": 40,
      "firstKillPercent": 10,
      "tradeKillPercent": 9.09,
      "ctKd": 0.8,
      "tKd": 0.43,
      "favoriteWeapon": {
        "weapon": "ak47",
        "kills": 4
      },
      "ratingS4N": 0.7,
      "mvpScore": 17.54
    },
    {
      "name": "⑧ ☆ kingC.- J",
      "steamid": "76561198810129628",
      "team": 3,
      "kills": 12,
      "assists": 4,
      "deaths": 17,
      "headshots": 2,
      "damage": 1240,
      "entryKills": 0,
      "entryDeaths": 1,
      "openingKills": 0,
      "openingDeaths": 1,
      "openingDuels": 1,
      "tradeKills": 2,
      "tradeOpportunities": 0,
      "awpKills": 3,
      "twoKs": 3,
      "threeKs": 1,
      "fourKs": 0,
      "aces": 0,
      "clutch1v1": 0,
      "clutch1v2": 1,
      "clutch1v3": 0,
      "clutch1v4": 0,
      "clutch1v5": 0,
      "baitRounds": 3,
      "kastRounds": 12,
      "heDamage": 21,
      "flashAssists": 1,
      "molotovDamage": 16,
      "ctKills": 9,
      "ctDeaths": 10,
      "tKills": 3,
      "tDeaths": 7,
      "weapons": {
        "ak47": 5,
        "awp": 3,
        "mac10": 1,
        "m4a1_silencer": 3
      },
      "diff": -5,
      "kd": 0.71,
      "hsPercent": 16.67,
      "adr": 62,
      "entryRatio": 0,
      "totalClutches": 1,
      "kastPercent": 60,
      "impactRating": 0.8,
      "openingDuelWinPercent": 0,
      "firstKillPercent": 0,
      "tradeKillPercent": 16.67,
      "ctKd": 0.9,
      "tKd": 0.43,
      "favoriteWeapon": {
        "weapon": "ak47",
        "kills": 5
      },
      "ratingS4N": 0.61,
      "mvpScore": 18.06
    },
    {
      "name": "⑧ Nicolas",
      "steamid": "76561199082720391",
      "team": 3,
      "kills": 9,
      "assists": 4,
      "deaths": 17,
      "headshots": 2,
      "damage": 1034,
      "entryKills": 2,
      "entryDeaths": 4,
      "openingKills": 2,
      "openingDeaths": 4,
      "openingDuels": 6,
      "tradeKills": 0,
      "tradeOpportunities": 0,
      "awpKills": 0,
      "twoKs": 1,
      "threeKs": 0,
      "fourKs": 0,
      "aces": 0,
      "clutch1v1": 0,
      "clutch1v2": 0,
      "clutch1v3": 0,
      "clutch1v4": 0,
      "clutch1v5": 0,
      "baitRounds": 6,
      "kastRounds": 12,
      "heDamage": 46,
      "flashAssists": 0,
      "molotovDamage": 0,
      "ctKills": 4,
      "ctDeaths": 10,
      "tKills": 5,
      "tDeaths": 7,
      "weapons": {
        "mac10": 1,
        "ak47": 3,
        "p250": 1,
        "m4a1_silencer": 3,
        "m4a1": 1
      },
      "diff": -8,
      "kd": 0.53,
      "hsPercent": 22.22,
      "adr": 51.7,
      "entryRatio": 0.5,
      "totalClutches": 0,
      "kastPercent": 60,
      "impactRating": 0.65,
      "openingDuelWinPercent": 33.33,
      "firstKillPercent": 10,
      "tradeKillPercent": 0,
      "ctKd": 0.4,
      "tKd": 0.71,
      "favoriteWeapon": {
        "weapon": "ak47",
        "kills": 3
      },
      "ratingS4N": 0.52,
      "mvpScore": 11.3
    }
  ],
  "createdAt": "2026-06-10T03:43:47.992Z"
}